MANIFEST.in
README.rst
setup.py
docs/HISTORY.txt
docs/INSTALL.txt
docs/LICENSE.GPL
docs/LICENSE.txt
docs/TODO.txt
unice/.DS_Store
unice/__init__.py
unice.portlet.evenementiels.egg-info/PKG-INFO
unice.portlet.evenementiels.egg-info/SOURCES.txt
unice.portlet.evenementiels.egg-info/dependency_links.txt
unice.portlet.evenementiels.egg-info/entry_points.txt
unice.portlet.evenementiels.egg-info/namespace_packages.txt
unice.portlet.evenementiels.egg-info/not-zip-safe
unice.portlet.evenementiels.egg-info/requires.txt
unice.portlet.evenementiels.egg-info/top_level.txt
unice/portlet/.DS_Store
unice/portlet/__init__.py
unice/portlet/evenementiels/.DS_Store
unice/portlet/evenementiels/__init__.py
unice/portlet/evenementiels/configure.zcml
unice/portlet/evenementiels/evenementielsportlet.pt
unice/portlet/evenementiels/evenementielsportlet.py
unice/portlet/evenementiels/vocabularies.py
unice/portlet/evenementiels/browser/.DS_Store
unice/portlet/evenementiels/browser/__init__.py
unice/portlet/evenementiels/browser/configure.zcml
unice/portlet/evenementiels/browser/stylesheets/styles.css
unice/portlet/evenementiels/profiles/.DS_Store
unice/portlet/evenementiels/profiles/default/cssregistry.xml
unice/portlet/evenementiels/profiles/default/metadata.xml
unice/portlet/evenementiels/profiles/default/portlets.xml
unice/portlet/evenementiels/tests/__init__.py
unice/portlet/evenementiels/tests/base.py
unice/portlet/evenementiels/tests/test_portlet.py